oliver_dl/__init__.py
oliver_dl/__main__.py
oliver_dl-0.1.0.dist-info/METADATA
oliver_dl-0.1.0.dist-info/WHEEL
oliver_dl-0.1.0.dist-info/RECORD
