Metadata-Version: 2.1
Name: oliver_dl
Version: 0.1.0
Summary: 
Author: Tumi Pare
Author-email: tumishangpare@gmail.com
Requires-Python: >=3.12,<4.0
Classifier: Programming Language :: Python :: 3
Classifier: Programming Language :: Python :: 3.12
Requires-Dist: aiohttp (>=3.9.1,<4.0.0)
Requires-Dist: progressbar2 (>=4.3.2,<5.0.0)
Requires-Dist: requests (>=2.31.0,<3.0.0)
